src/__init__.py
src/main.py
src/ieca/__init__.py
src/ieca/actividad.py
src/ieca/consulta.py
src/ieca/datos.py
src/ieca/jerarquia.py
src/utiles/__init__.py
src/utiles/embellecedor_metadatos.py
src/utiles/traducir.py
src/utiles/validador.py
src/utiles/metadatos/__init__.py
ieca2sdmx-1.0.0.dist-info/METADATA
ieca2sdmx-1.0.0.dist-info/WHEEL
ieca2sdmx-1.0.0.dist-info/top_level.txt
ieca2sdmx-1.0.0.dist-info/RECORD
