Metadata-Version: 2.1
Name: ieca2sdmx
Version: 1.0.0
Summary: Transformación de datos y metadatos desde el IECA hacia SDMX
Home-page: https://github.com/frapercan/IECA2SDMX
Author: frapercan
Author-email: frapercan1@alum.us.es
License: MIT
Platform: UNKNOWN
Classifier: Development Status :: 2 - Pre-Alpha
Classifier: License :: OSI Approved :: MIT License
Classifier: Programming Language :: Python :: 3.10
